.gitignore
CHANGELOG.md
LICENSE
MANIFEST.in
README.md
pyproject.toml
setup.cfg
setup.py
.github/workflows/build.yaml
picnic/__init__.py
picnic/_picnic.pyi
picnic/_picnic.pyx
picnic/cpicnic.pxd
picnic/helper_functions.h
picnic/py.typed
picnic/tests/__init__.py
picnic/tests/kat_l1_fs.txt
picnic/tests/kat_l1_full.txt
picnic/tests/kat_l1_ur.txt
picnic/tests/kat_l3_fs.txt
picnic/tests/kat_l3_full.txt
picnic/tests/kat_l3_ur.txt
picnic/tests/kat_l5_fs.txt
picnic/tests/kat_l5_full.txt
picnic/tests/kat_l5_ur.txt
picnic/tests/kat_picnic3_l1.txt
picnic/tests/kat_picnic3_l3.txt
picnic/tests/kat_picnic3_l5.txt
picnic/tests/test_picnic.py
python_picnic.egg-info/PKG-INFO
python_picnic.egg-info/SOURCES.txt
python_picnic.egg-info/dependency_links.txt
python_picnic.egg-info/not-zip-safe
python_picnic.egg-info/top_level.txt