Metadata-Version: 2.1
Name: python-picnic
Version: 1.0.1
Summary: Python bindings for picnic
Home-page: https://github.com/sebastinas/python-picnic
Author: Sebastian Ramacher
Author-email: sebastian.ramacher@ait.ac.at
License: MIT
Platform: UNKNOWN
Classifier: Development Status :: 4 - Beta
Classifier: Intended Audience :: Developers
Classifier: License :: OSI Approved :: MIT License
Classifier: Operating System :: OS Independent
Classifier: Programming Language :: Python :: 3
Classifier: Programming Language :: Python :: 3.6
Classifier: Programming Language :: Python :: 3.7
Classifier: Programming Language :: Python :: 3.8
Classifier: Topic :: Software Development :: Libraries :: Python Modules
Classifier: Topic :: Security :: Cryptography
Requires-Python: >=3.7
License-File: LICENSE
